{
"instructions_readme": "1) Open Chrome, 2) go to chrome://tracing, 3) click Load, 4) navigate to this file.",

"traceEvents":[
{ "pid": 1, "tid": 1, "ph": "M", "name": "thread_name", "args": { "name": "Main thread" } },
{ "pid": 1, "tid": 1, "ts": 709.6999883651733, "dur": 38124000, "ph": "X", "name": "il2cpp.exe", "args": { "durationMS": 38124, "detail": "" } },
{ "pid": 1, "tid": 1, "ts": 56012.59994506836, "dur": 38067191.40625, "ph": "X", "name": "Build", "args": { "durationMS": 38067.19140625, "detail": "" } },
{ "pid": 1, "tid": 1, "ts": 56214.70260620117, "dur": 166509.50622558594, "ph": "X", "name": "FindFilesToCompile", "args": { "durationMS": 166.50950622558594, "detail": "" } },
{ "pid": 1, "tid": 1, "ts": 222841.5985107422, "dur": 155740.90576171875, "ph": "X", "name": "Calculate header hashes", "args": { "durationMS": 155.74090576171875, "detail": "" } },
{ "pid": 1, "tid": 1, "ts": 378582.82470703125, "dur": 20473.69956970215, "ph": "X", "name": "Calculate lumped hashes", "args": { "durationMS": 20.47369956970215, "detail": "" } },
{ "pid": 1, "tid": 1, "ts": 399160.400390625, "dur": 3526479.00390625, "ph": "X", "name": "Compile All Files", "args": { "durationMS": 3526.47900390625, "detail": "" } },
{ "pid": 1, "tid": 1, "ts": 3925653.80859375, "dur": 516.700029373169, "ph": "X", "name": "OnBeforeLink Build", "args": { "durationMS": 0.516700029373169, "detail": "" } },
{ "pid": 1, "tid": 1, "ts": 3926177.490234375, "dur": 33480718.75, "ph": "X", "name": "Link", "args": { "durationMS": 33480.71875, "detail": "libil2cpp.so" } },
{ "pid": 1, "tid": 1, "ts": 3940376.953125, "dur": 42177.70004272461, "ph": "X", "name": "hash linker invocation", "args": { "durationMS": 42.17770004272461, "detail": "" } },
{ "pid": 1, "tid": 1, "ts": 4058571.044921875, "dur": 28350369.140625, "ph": "X", "name": "ActualLinkerInvocation", "args": { "durationMS": 28350.369140625, "detail": "libil2cpp.so" } },
{ "pid": 1, "tid": 1, "ts": 32409173.828125, "dur": 1677926.7578125, "ph": "X", "name": "ToolChain OnAfterLink Build", "args": { "durationMS": 1677.9267578125, "detail": "" } },
{ "pid": 1, "tid": 1, "ts": 32417208.984375, "dur": 538155.029296875, "ph": "X", "name": "strip", "args": { "durationMS": 538.155029296875, "detail": "" } },
{ "pid": 1, "tid": 1, "ts": 32955410.15625, "dur": 719765.3198242188, "ph": "X", "name": "strip", "args": { "durationMS": 719.7653198242188, "detail": "debug" } },
{ "pid": 1, "tid": 1, "ts": 33675207.03125, "dur": 411889.6789550781, "ph": "X", "name": "strip", "args": { "durationMS": 411.8896789550781, "detail": "debug link" } },
{ "pid": 1, "tid": 1, "ts": 34087101.5625, "dur": 3319580.56640625, "ph": "X", "name": "Copy from cache to output directory", "args": { "durationMS": 3319.58056640625, "detail": "" } },
{ "pid": 1, "tid": 1, "ts": 37406898.4375, "dur": 640811.03515625, "ph": "X", "name": "ProgramDescription Finalize Build", "args": { "durationMS": 640.81103515625, "detail": "" } },
{ "pid": 1, "tid": 1, "ts": 38047707.03125, "dur": 75494.00329589844, "ph": "X", "name": "Clean IL2CPP Cache", "args": { "durationMS": 75.49400329589844, "detail": "" } },
{ "pid": 1, "tid": 5, "ph": "M", "name": "thread_name", "args": { "name": "" } },
{ "pid": 1, "tid": 5, "ts": 279306.1218261719, "dur": 99123.39782714844, "ph": "X", "name": "FileHashProvider.Initialize", "args": { "durationMS": 99.12339782714844, "detail": "." } },
{ "pid": 1, "tid": 5, "ts": 280345.703125, "dur": 97048.50006103516, "ph": "X", "name": "HashOfAllFilesWithProviderExtensionInDirectory", "args": { "durationMS": 97.04850006103516, "detail": ".h ." } },
{ "pid": 1, "tid": 5, "ts": 377398.98681640625, "dur": 1029.099941253662, "ph": "X", "name": "HashOfAllFilesWithProviderExtensionInDirectory", "args": { "durationMS": 1.029099941253662, "detail": ".inc ." } },
{ "pid": 1, "tid": 6, "ph": "M", "name": "thread_name", "args": { "name": "" } },
{ "pid": 1, "tid": 6, "ts": 279345.39794921875, "dur": 30899.398803710938, "ph": "X", "name": "FileHashProvider.Initialize", "args": { "durationMS": 30.899398803710938, "detail": "C:\\Program Files\\Unity\\Hub\\Editor\\2021.1.16f1\\Editor\\Data\\il2cpp\\external\\baselib\\Include" } },
{ "pid": 1, "tid": 6, "ts": 280371.9787597656, "dur": 28889.60075378418, "ph": "X", "name": "HashOfAllFilesWithProviderExtensionInDirectory", "args": { "durationMS": 28.88960075378418, "detail": ".h C:\\Program Files\\Unity\\Hub\\Editor\\2021.1.16f1\\Editor\\Data\\il2cpp\\external\\baselib\\Include" } },
{ "pid": 1, "tid": 6, "ts": 309265.19775390625, "dur": 975.7999777793884, "ph": "X", "name": "HashOfAllFilesWithProviderExtensionInDirectory", "args": { "durationMS": 0.9757999777793884, "detail": ".inc C:\\Program Files\\Unity\\Hub\\Editor\\2021.1.16f1\\Editor\\Data\\il2cpp\\external\\baselib\\Include" } },
{ "pid": 1, "tid": 6, "ts": 310245.8190917969, "dur": 1023.4999656677246, "ph": "X", "name": "FileHashProvider.Initialize", "args": { "durationMS": 1.0234999656677246, "detail": "C:\\Program Files\\Unity\\Hub\\Editor\\2021.1.16f1\\Editor\\Data\\il2cpp\\libil2cpp\\pch" } },
{ "pid": 1, "tid": 6, "ts": 310249.0234375, "dur": 554.0000200271606, "ph": "X", "name": "HashOfAllFilesWithProviderExtensionInDirectory", "args": { "durationMS": 0.5540000200271606, "detail": ".h C:\\Program Files\\Unity\\Hub\\Editor\\2021.1.16f1\\Editor\\Data\\il2cpp\\libil2cpp\\pch" } },
{ "pid": 1, "tid": 6, "ts": 310806.396484375, "dur": 461.49998903274536, "ph": "X", "name": "HashOfAllFilesWithProviderExtensionInDirectory", "args": { "durationMS": 0.46149998903274536, "detail": ".inc C:\\Program Files\\Unity\\Hub\\Editor\\2021.1.16f1\\Editor\\Data\\il2cpp\\libil2cpp\\pch" } },
{ "pid": 1, "tid": 6, "ts": 311270.5078125, "dur": 35799.49951171875, "ph": "X", "name": "FileHashProvider.Initialize", "args": { "durationMS": 35.79949951171875, "detail": "F:\\Jogo 2D\\Jogo2D\\Library\\Il2cppBuildCache\\Android\\armeabi-v7a\\il2cppOutput" } },
{ "pid": 1, "tid": 6, "ts": 311274.0173339844, "dur": 18843.599319458008, "ph": "X", "name": "HashOfAllFilesWithProviderExtensionInDirectory", "args": { "durationMS": 18.843599319458008, "detail": ".h F:\\Jogo 2D\\Jogo2D\\Library\\Il2cppBuildCache\\Android\\armeabi-v7a\\il2cppOutput" } },
{ "pid": 1, "tid": 6, "ts": 330123.291015625, "dur": 16945.100784301758, "ph": "X", "name": "HashOfAllFilesWithProviderExtensionInDirectory", "args": { "durationMS": 16.945100784301758, "detail": ".inc F:\\Jogo 2D\\Jogo2D\\Library\\Il2cppBuildCache\\Android\\armeabi-v7a\\il2cppOutput" } },
{ "pid": 1, "tid": 7, "ph": "M", "name": "thread_name", "args": { "name": "" } },
{ "pid": 1, "tid": 7, "ts": 279380.4016113281, "dur": 27979.398727416992, "ph": "X", "name": "FileHashProvider.Initialize", "args": { "durationMS": 27.979398727416992, "detail": "C:\\Program Files\\Unity\\Hub\\Editor\\2021.1.16f1\\Editor\\Data\\il2cpp\\external\\baselib\\Platforms\\Android\\Include" } },
{ "pid": 1, "tid": 7, "ts": 280402.9846191406, "dur": 26408.199310302734, "ph": "X", "name": "HashOfAllFilesWithProviderExtensionInDirectory", "args": { "durationMS": 26.408199310302734, "detail": ".h C:\\Program Files\\Unity\\Hub\\Editor\\2021.1.16f1\\Editor\\Data\\il2cpp\\external\\baselib\\Platforms\\Android\\Include" } },
{ "pid": 1, "tid": 7, "ts": 306824.0966796875, "dur": 533.2000255584717, "ph": "X", "name": "HashOfAllFilesWithProviderExtensionInDirectory", "args": { "durationMS": 0.5332000255584717, "detail": ".inc C:\\Program Files\\Unity\\Hub\\Editor\\2021.1.16f1\\Editor\\Data\\il2cpp\\external\\baselib\\Platforms\\Android\\Include" } },
{ "pid": 1, "tid": 7, "ts": 307370.1171875, "dur": 5501.500129699707, "ph": "X", "name": "FileHashProvider.Initialize", "args": { "durationMS": 5.501500129699707, "detail": "C:\\Program Files\\Unity\\Hub\\Editor\\2021.1.16f1\\Editor\\Data\\il2cpp\\external\\bdwgc\\libatomic_ops\\src" } },
{ "pid": 1, "tid": 7, "ts": 307376.89208984375, "dur": 4641.39986038208, "ph": "X", "name": "HashOfAllFilesWithProviderExtensionInDirectory", "args": { "durationMS": 4.64139986038208, "detail": ".h C:\\Program Files\\Unity\\Hub\\Editor\\2021.1.16f1\\Editor\\Data\\il2cpp\\external\\bdwgc\\libatomic_ops\\src" } },
{ "pid": 1, "tid": 7, "ts": 312022.0947265625, "dur": 846.4999794960022, "ph": "X", "name": "HashOfAllFilesWithProviderExtensionInDirectory", "args": { "durationMS": 0.8464999794960022, "detail": ".inc C:\\Program Files\\Unity\\Hub\\Editor\\2021.1.16f1\\Editor\\Data\\il2cpp\\external\\bdwgc\\libatomic_ops\\src" } },
{ "pid": 1, "tid": 8, "ph": "M", "name": "thread_name", "args": { "name": "" } },
{ "pid": 1, "tid": 8, "ts": 279412.9943847656, "dur": 28206.39991760254, "ph": "X", "name": "FileHashProvider.Initialize", "args": { "durationMS": 28.20639991760254, "detail": "C:\\Program Files\\Unity\\Hub\\Editor\\2021.1.16f1\\Editor\\Data\\il2cpp\\external\\bdwgc\\include" } },
{ "pid": 1, "tid": 8, "ts": 280350.89111328125, "dur": 26634.498596191406, "ph": "X", "name": "HashOfAllFilesWithProviderExtensionInDirectory", "args": { "durationMS": 26.634498596191406, "detail": ".h C:\\Program Files\\Unity\\Hub\\Editor\\2021.1.16f1\\Editor\\Data\\il2cpp\\external\\bdwgc\\include" } },
{ "pid": 1, "tid": 8, "ts": 306989.501953125, "dur": 625.9999871253967, "ph": "X", "name": "HashOfAllFilesWithProviderExtensionInDirectory", "args": { "durationMS": 0.6259999871253967, "detail": ".inc C:\\Program Files\\Unity\\Hub\\Editor\\2021.1.16f1\\Editor\\Data\\il2cpp\\external\\bdwgc\\include" } },
{ "pid": 1, "tid": 8, "ts": 307620.3918457031, "dur": 1741.0000562667847, "ph": "X", "name": "FileHashProvider.Initialize", "args": { "durationMS": 1.7410000562667847, "detail": "C:\\Program Files\\Unity\\Hub\\Editor\\2021.1.16f1\\Editor\\Data\\il2cpp\\external\\xxHash" } },
{ "pid": 1, "tid": 8, "ts": 307623.8098144531, "dur": 1067.8000450134277, "ph": "X", "name": "HashOfAllFilesWithProviderExtensionInDirectory", "args": { "durationMS": 1.0678000450134277, "detail": ".h C:\\Program Files\\Unity\\Hub\\Editor\\2021.1.16f1\\Editor\\Data\\il2cpp\\external\\xxHash" } },
{ "pid": 1, "tid": 8, "ts": 308702.4230957031, "dur": 657.5999855995178, "ph": "X", "name": "HashOfAllFilesWithProviderExtensionInDirectory", "args": { "durationMS": 0.6575999855995178, "detail": ".inc C:\\Program Files\\Unity\\Hub\\Editor\\2021.1.16f1\\Editor\\Data\\il2cpp\\external\\xxHash" } },
{ "pid": 1, "tid": 8, "ts": 309362.7014160156, "dur": 27475.59928894043, "ph": "X", "name": "FileHashProvider.Initialize", "args": { "durationMS": 27.47559928894043, "detail": "C:\\Program Files\\Unity\\Hub\\Editor\\2021.1.16f1\\Editor\\Data\\il2cpp\\libil2cpp" } },
{ "pid": 1, "tid": 8, "ts": 309365.5090332031, "dur": 23770.898818969727, "ph": "X", "name": "HashOfAllFilesWithProviderExtensionInDirectory", "args": { "durationMS": 23.770898818969727, "detail": ".h C:\\Program Files\\Unity\\Hub\\Editor\\2021.1.16f1\\Editor\\Data\\il2cpp\\libil2cpp" } },
{ "pid": 1, "tid": 8, "ts": 333140.1062011719, "dur": 3673.1998920440674, "ph": "X", "name": "HashOfAllFilesWithProviderExtensionInDirectory", "args": { "durationMS": 3.6731998920440674, "detail": ".inc C:\\Program Files\\Unity\\Hub\\Editor\\2021.1.16f1\\Editor\\Data\\il2cpp\\libil2cpp" } },
{ "pid": 1, "tid": 11, "ph": "M", "name": "thread_name", "args": { "name": "" } },
{ "pid": 1, "tid": 11, "ts": 300462.70751953125, "dur": 4088.099956512451, "ph": "X", "name": "HashOfFile", "args": { "durationMS": 4.088099956512451, "detail": "C:\\Program Files\\Unity\\Hub\\Editor\\2021.1.16f1\\Editor\\Data\\il2cpp\\external\\bdwgc\\include\\cord.h" } },
{ "pid": 1, "tid": 11, "ts": 304938.90380859375, "dur": 419.6999967098236, "ph": "X", "name": "HashOfFile", "args": { "durationMS": 0.4196999967098236, "detail": "C:\\Program Files\\Unity\\Hub\\Editor\\2021.1.16f1\\Editor\\Data\\il2cpp\\external\\bdwgc\\include\\gc.h" } },
{ "pid": 1, "tid": 11, "ts": 306136.0168457031, "dur": 406.8000018596649, "ph": "X", "name": "HashOfFile", "args": { "durationMS": 0.4068000018596649, "detail": "C:\\Program Files\\Unity\\Hub\\Editor\\2021.1.16f1\\Editor\\Data\\il2cpp\\external\\bdwgc\\include\\private\\gcconfig.h" } },
{ "pid": 1, "tid": 14, "ph": "M", "name": "thread_name", "args": { "name": "" } },
{ "pid": 1, "tid": 14, "ts": 300472.59521484375, "dur": 4144.499778747559, "ph": "X", "name": "HashOfFile", "args": { "durationMS": 4.144499778747559, "detail": "C:\\Program Files\\Unity\\Hub\\Editor\\2021.1.16f1\\Editor\\Data\\il2cpp\\external\\baselib\\Include\\C\\Baselib_Alignment.h" } },
{ "pid": 1, "tid": 9, "ph": "M", "name": "thread_name", "args": { "name": "" } },
{ "pid": 1, "tid": 9, "ts": 300484.0087890625, "dur": 4067.3999786376953, "ph": "X", "name": "HashOfFile", "args": { "durationMS": 4.067399978637695, "detail": "C:\\Program Files\\Unity\\Hub\\Editor\\2021.1.16f1\\Editor\\Data\\il2cpp\\external\\baselib\\Platforms\\Android\\Include\\BaselibPlatformSpecificEnvironment.h" } },
{ "pid": 1, "tid": 12, "ph": "M", "name": "thread_name", "args": { "name": "" } },
{ "pid": 1, "tid": 12, "ts": 300521.17919921875, "dur": 4029.600143432617, "ph": "X", "name": "HashOfFile", "args": { "durationMS": 4.029600143432617, "detail": "C:\\Program Files\\Unity\\Hub\\Editor\\2021.1.16f1\\Editor\\Data\\il2cpp\\external\\bdwgc\\include\\cord_pos.h" } },
{ "pid": 1, "tid": 12, "ts": 306072.509765625, "dur": 370.2999949455261, "ph": "X", "name": "HashOfFile", "args": { "durationMS": 0.3702999949455261, "detail": "C:\\Program Files\\Unity\\Hub\\Editor\\2021.1.16f1\\Editor\\Data\\il2cpp\\external\\bdwgc\\include\\private\\gc_priv.h" } },
{ "pid": 1, "tid": 10, "ph": "M", "name": "thread_name", "args": { "name": "" } },
{ "pid": 1, "tid": 10, "ts": 300552.6123046875, "dur": 3998.6000061035156, "ph": "X", "name": "HashOfFile", "args": { "durationMS": 3.9986000061035156, "detail": "C:\\Program Files\\Unity\\Hub\\Editor\\2021.1.16f1\\Editor\\Data\\il2cpp\\external\\baselib\\Platforms\\Android\\Include\\C\\Baselib_DynamicLibrary.inl.h" } },
{ "pid": 1, "tid": 13, "ph": "M", "name": "thread_name", "args": { "name": "" } },
{ "pid": 1, "tid": 13, "ts": 300591.4001464844, "dur": 4085.4997634887695, "ph": "X", "name": "HashOfFile", "args": { "durationMS": 4.0854997634887695, "detail": "C:\\Program Files\\Unity\\Hub\\Editor\\2021.1.16f1\\Editor\\Data\\il2cpp\\external\\baselib\\Include\\Baselib.h" } },
{ "pid": 1, "tid": 21, "ph": "M", "name": "thread_name", "args": { "name": "" } },
{ "pid": 1, "tid": 21, "ts": 308800.6896972656, "dur": 486.299991607666, "ph": "X", "name": "HashOfFile", "args": { "durationMS": 0.486299991607666, "detail": "C:\\Program Files\\Unity\\Hub\\Editor\\2021.1.16f1\\Editor\\Data\\il2cpp\\external\\bdwgc\\libatomic_ops\\src\\atomic_ops\\generalize-arithm.h" } },
{ "pid": 1, "tid": 22, "ph": "M", "name": "thread_name", "args": { "name": "" } },
{ "pid": 1, "tid": 22, "ts": 309065.00244140625, "dur": 471.10000252723694, "ph": "X", "name": "HashOfFile", "args": { "durationMS": 0.47110000252723694, "detail": "C:\\Program Files\\Unity\\Hub\\Editor\\2021.1.16f1\\Editor\\Data\\il2cpp\\external\\bdwgc\\libatomic_ops\\src\\atomic_ops\\generalize-small.h" } },
{ "pid": 1, "tid": 33, "ph": "M", "name": "thread_name", "args": { "name": "" } },
{ "pid": 1, "tid": 33, "ts": 323804.50439453125, "dur": 704.4000029563904, "ph": "X", "name": "HashOfFile", "args": { "durationMS": 0.7044000029563904, "detail": "C:\\Program Files\\Unity\\Hub\\Editor\\2021.1.16f1\\Editor\\Data\\il2cpp\\libil2cpp\\il2cpp-normalization-tables.h" } },
{ "pid": 1, "tid": 34, "ph": "M", "name": "thread_name", "args": { "name": "" } },
{ "pid": 1, "tid": 34, "ts": 319661.80419921875, "dur": 1456.5000534057617, "ph": "X", "name": "HashOfFile", "args": { "durationMS": 1.4565000534057617, "detail": "C:\\Program Files\\Unity\\Hub\\Editor\\2021.1.16f1\\Editor\\Data\\il2cpp\\libil2cpp\\icalls\\mscorlib\\System.Globalization\\Generated\\CultureInfoTablesNet_4_0.h" } },
{ "pid": 1, "tid": 45, "ph": "M", "name": "thread_name", "args": { "name": "" } },
{ "pid": 1, "tid": 45, "ts": 379603.8818359375, "dur": 9860.899925231934, "ph": "X", "name": "FileHashProvider.Initialize", "args": { "durationMS": 9.860899925231934, "detail": "C:\\Program Files\\Unity\\Hub\\Editor\\2021.1.16f1\\Editor\\Data\\il2cpp\\external\\bdwgc" } },
{ "pid": 1, "tid": 45, "ts": 379610.5041503906, "dur": 2478.4998893737793, "ph": "X", "name": "HashOfAllFilesWithProviderExtensionInDirectory", "args": { "durationMS": 2.4784998893737793, "detail": ".cpp C:\\Program Files\\Unity\\Hub\\Editor\\2021.1.16f1\\Editor\\Data\\il2cpp\\external\\bdwgc" } },
{ "pid": 1, "tid": 45, "ts": 382092.59033203125, "dur": 7368.599891662598, "ph": "X", "name": "HashOfAllFilesWithProviderExtensionInDirectory", "args": { "durationMS": 7.368599891662598, "detail": ".c C:\\Program Files\\Unity\\Hub\\Editor\\2021.1.16f1\\Editor\\Data\\il2cpp\\external\\bdwgc" } },
{ "pid": 1, "tid": 45, "ts": 389466.00341796875, "dur": 7837.800025939941, "ph": "X", "name": "FileHashProvider.Initialize", "args": { "durationMS": 7.837800025939941, "detail": "C:\\Program Files\\Unity\\Hub\\Editor\\2021.1.16f1\\Editor\\Data\\il2cpp\\libil2cpp\\vm" } },
{ "pid": 1, "tid": 45, "ts": 389470.21484375, "dur": 6674.600124359131, "ph": "X", "name": "HashOfAllFilesWithProviderExtensionInDirectory", "args": { "durationMS": 6.674600124359131, "detail": ".cpp C:\\Program Files\\Unity\\Hub\\Editor\\2021.1.16f1\\Editor\\Data\\il2cpp\\libil2cpp\\vm" } },
{ "pid": 1, "tid": 45, "ts": 396147.7966308594, "dur": 1152.7999639511108, "ph": "X", "name": "HashOfAllFilesWithProviderExtensionInDirectory", "args": { "durationMS": 1.1527999639511108, "detail": ".c C:\\Program Files\\Unity\\Hub\\Editor\\2021.1.16f1\\Editor\\Data\\il2cpp\\libil2cpp\\vm" } },
{ "pid": 1, "tid": 46, "ph": "M", "name": "thread_name", "args": { "name": "" } },
{ "pid": 1, "tid": 46, "ts": 380481.2927246094, "dur": 1765.2000188827515, "ph": "X", "name": "FileHashProvider.Initialize", "args": { "durationMS": 1.7652000188827515, "detail": "C:\\Program Files\\Unity\\Hub\\Editor\\2021.1.16f1\\Editor\\Data\\il2cpp\\libil2cpp\\codegen" } },
{ "pid": 1, "tid": 46, "ts": 380487.48779296875, "dur": 1248.2999563217163, "ph": "X", "name": "HashOfAllFilesWithProviderExtensionInDirectory", "args": { "durationMS": 1.2482999563217163, "detail": ".cpp C:\\Program Files\\Unity\\Hub\\Editor\\2021.1.16f1\\Editor\\Data\\il2cpp\\libil2cpp\\codegen" } },
{ "pid": 1, "tid": 46, "ts": 381738.58642578125, "dur": 506.69997930526733, "ph": "X", "name": "HashOfAllFilesWithProviderExtensionInDirectory", "args": { "durationMS": 0.5066999793052673, "detail": ".c C:\\Program Files\\Unity\\Hub\\Editor\\2021.1.16f1\\Editor\\Data\\il2cpp\\libil2cpp\\codegen" } },
{ "pid": 1, "tid": 46, "ts": 382247.802734375, "dur": 1843.7000513076782, "ph": "X", "name": "FileHashProvider.Initialize", "args": { "durationMS": 1.8437000513076782, "detail": "C:\\Program Files\\Unity\\Hub\\Editor\\2021.1.16f1\\Editor\\Data\\il2cpp\\libil2cpp\\metadata" } },
{ "pid": 1, "tid": 46, "ts": 382250.91552734375, "dur": 1436.1000061035156, "ph": "X", "name": "HashOfAllFilesWithProviderExtensionInDirectory", "args": { "durationMS": 1.4361000061035156, "detail": ".cpp C:\\Program Files\\Unity\\Hub\\Editor\\2021.1.16f1\\Editor\\Data\\il2cpp\\libil2cpp\\metadata" } },
{ "pid": 1, "tid": 46, "ts": 383690.12451171875, "dur": 399.69998598098755, "ph": "X", "name": "HashOfAllFilesWithProviderExtensionInDirectory", "args": { "durationMS": 0.39969998598098755, "detail": ".c C:\\Program Files\\Unity\\Hub\\Editor\\2021.1.16f1\\Editor\\Data\\il2cpp\\libil2cpp\\metadata" } },
{ "pid": 1, "tid": 46, "ts": 384092.4987792969, "dur": 14368.000030517578, "ph": "X", "name": "FileHashProvider.Initialize", "args": { "durationMS": 14.368000030517578, "detail": "C:\\Program Files\\Unity\\Hub\\Editor\\2021.1.16f1\\Editor\\Data\\il2cpp\\libil2cpp\\os" } },
{ "pid": 1, "tid": 46, "ts": 384095.5810546875, "dur": 13019.800186157227, "ph": "X", "name": "HashOfAllFilesWithProviderExtensionInDirectory", "args": { "durationMS": 13.019800186157227, "detail": ".cpp C:\\Program Files\\Unity\\Hub\\Editor\\2021.1.16f1\\Editor\\Data\\il2cpp\\libil2cpp\\os" } },
{ "pid": 1, "tid": 46, "ts": 397118.408203125, "dur": 1335.1000547409058, "ph": "X", "name": "HashOfAllFilesWithProviderExtensionInDirectory", "args": { "durationMS": 1.3351000547409058, "detail": ".c C:\\Program Files\\Unity\\Hub\\Editor\\2021.1.16f1\\Editor\\Data\\il2cpp\\libil2cpp\\os" } },
{ "pid": 1, "tid": 47, "ph": "M", "name": "thread_name", "args": { "name": "" } },
{ "pid": 1, "tid": 47, "ts": 380504.3029785156, "dur": 1652.6000499725342, "ph": "X", "name": "FileHashProvider.Initialize", "args": { "durationMS": 1.6526000499725342, "detail": "C:\\Program Files\\Unity\\Hub\\Editor\\2021.1.16f1\\Editor\\Data\\il2cpp\\libil2cpp\\debugger" } },
{ "pid": 1, "tid": 47, "ts": 380508.7890625, "dur": 1034.7000360488892, "ph": "X", "name": "HashOfAllFilesWithProviderExtensionInDirectory", "args": { "durationMS": 1.0347000360488892, "detail": ".cpp C:\\Program Files\\Unity\\Hub\\Editor\\2021.1.16f1\\Editor\\Data\\il2cpp\\libil2cpp\\debugger" } },
{ "pid": 1, "tid": 47, "ts": 381547.91259765625, "dur": 607.699990272522, "ph": "X", "name": "HashOfAllFilesWithProviderExtensionInDirectory", "args": { "durationMS": 0.607699990272522, "detail": ".c C:\\Program Files\\Unity\\Hub\\Editor\\2021.1.16f1\\Editor\\Data\\il2cpp\\libil2cpp\\debugger" } },
{ "pid": 1, "tid": 47, "ts": 382158.1115722656, "dur": 16808.700561523438, "ph": "X", "name": "FileHashProvider.Initialize", "args": { "durationMS": 16.808700561523438, "detail": "C:\\Program Files\\Unity\\Hub\\Editor\\2021.1.16f1\\Editor\\Data\\il2cpp\\libil2cpp\\icalls" } },
{ "pid": 1, "tid": 47, "ts": 382161.31591796875, "dur": 13652.799606323242, "ph": "X", "name": "HashOfAllFilesWithProviderExtensionInDirectory", "args": { "durationMS": 13.652799606323242, "detail": ".cpp C:\\Program Files\\Unity\\Hub\\Editor\\2021.1.16f1\\Editor\\Data\\il2cpp\\libil2cpp\\icalls" } },
{ "pid": 1, "tid": 47, "ts": 395816.89453125, "dur": 3145.6000804901123, "ph": "X", "name": "HashOfAllFilesWithProviderExtensionInDirectory", "args": { "durationMS": 3.1456000804901123, "detail": ".c C:\\Program Files\\Unity\\Hub\\Editor\\2021.1.16f1\\Editor\\Data\\il2cpp\\libil2cpp\\icalls" } },
{ "pid": 1, "tid": 48, "ph": "M", "name": "thread_name", "args": { "name": "" } },
{ "pid": 1, "tid": 48, "ts": 380795.5017089844, "dur": 1714.300036430359, "ph": "X", "name": "FileHashProvider.Initialize", "args": { "durationMS": 1.7143000364303589, "detail": "C:\\Program Files\\Unity\\Hub\\Editor\\2021.1.16f1\\Editor\\Data\\il2cpp\\libil2cpp\\gc" } },
{ "pid": 1, "tid": 48, "ts": 380800.4150390625, "dur": 1352.8000116348267, "ph": "X", "name": "HashOfAllFilesWithProviderExtensionInDirectory", "args": { "durationMS": 1.3528000116348267, "detail": ".cpp C:\\Program Files\\Unity\\Hub\\Editor\\2021.1.16f1\\Editor\\Data\\il2cpp\\libil2cpp\\gc" } },
{ "pid": 1, "tid": 48, "ts": 382156.2194824219, "dur": 351.5999913215637, "ph": "X", "name": "HashOfAllFilesWithProviderExtensionInDirectory", "args": { "durationMS": 0.3515999913215637, "detail": ".c C:\\Program Files\\Unity\\Hub\\Editor\\2021.1.16f1\\Editor\\Data\\il2cpp\\libil2cpp\\gc" } },
{ "pid": 1, "tid": 48, "ts": 382510.8947753906, "dur": 1652.6999473571777, "ph": "X", "name": "FileHashProvider.Initialize", "args": { "durationMS": 1.6526999473571777, "detail": "C:\\Program Files\\Unity\\Hub\\Editor\\2021.1.16f1\\Editor\\Data\\il2cpp\\libil2cpp\\mono" } },
{ "pid": 1, "tid": 48, "ts": 382513.61083984375, "dur": 1209.3000411987305, "ph": "X", "name": "HashOfAllFilesWithProviderExtensionInDirectory", "args": { "durationMS": 1.2093000411987305, "detail": ".cpp C:\\Program Files\\Unity\\Hub\\Editor\\2021.1.16f1\\Editor\\Data\\il2cpp\\libil2cpp\\mono" } },
{ "pid": 1, "tid": 48, "ts": 383725.7995605469, "dur": 435.7999861240387, "ph": "X", "name": "HashOfAllFilesWithProviderExtensionInDirectory", "args": { "durationMS": 0.4357999861240387, "detail": ".c C:\\Program Files\\Unity\\Hub\\Editor\\2021.1.16f1\\Editor\\Data\\il2cpp\\libil2cpp\\mono" } },
{ "pid": 1, "tid": 48, "ts": 384164.8254394531, "dur": 11443.79997253418, "ph": "X", "name": "FileHashProvider.Initialize", "args": { "durationMS": 11.44379997253418, "detail": "C:\\Program Files\\Unity\\Hub\\Editor\\2021.1.16f1\\Editor\\Data\\il2cpp\\libil2cpp\\utils" } },
{ "pid": 1, "tid": 48, "ts": 384167.6025390625, "dur": 2216.399908065796, "ph": "X", "name": "HashOfAllFilesWithProviderExtensionInDirectory", "args": { "durationMS": 2.216399908065796, "detail": ".cpp C:\\Program Files\\Unity\\Hub\\Editor\\2021.1.16f1\\Editor\\Data\\il2cpp\\libil2cpp\\utils" } },
{ "pid": 1, "tid": 48, "ts": 386388.7023925781, "dur": 9217.100143432617, "ph": "X", "name": "HashOfAllFilesWithProviderExtensionInDirectory", "args": { "durationMS": 9.217100143432617, "detail": ".c C:\\Program Files\\Unity\\Hub\\Editor\\2021.1.16f1\\Editor\\Data\\il2cpp\\libil2cpp\\utils" } },
{ "pid": 1, "tid": 48, "ts": 395609.80224609375, "dur": 2258.500099182129, "ph": "X", "name": "FileHashProvider.Initialize", "args": { "durationMS": 2.258500099182129, "detail": "C:\\Program Files\\Unity\\Hub\\Editor\\2021.1.16f1\\Editor\\Data\\il2cpp\\libil2cpp\\vm-utils" } },
{ "pid": 1, "tid": 48, "ts": 395616.2109375, "dur": 1678.0999898910522, "ph": "X", "name": "HashOfAllFilesWithProviderExtensionInDirectory", "args": { "durationMS": 1.6780999898910522, "detail": ".cpp C:\\Program Files\\Unity\\Hub\\Editor\\2021.1.16f1\\Editor\\Data\\il2cpp\\libil2cpp\\vm-utils" } },
{ "pid": 1, "tid": 48, "ts": 397303.4973144531, "dur": 563.6000037193298, "ph": "X", "name": "HashOfAllFilesWithProviderExtensionInDirectory", "args": { "durationMS": 0.5636000037193298, "detail": ".c C:\\Program Files\\Unity\\Hub\\Editor\\2021.1.16f1\\Editor\\Data\\il2cpp\\libil2cpp\\vm-utils" } },
{ "pid": 1, "tid": 72, "ph": "M", "name": "thread_name", "args": { "name": "" } },
{ "pid": 1, "tid": 72, "ts": 387264.1906738281, "dur": 554.7000169754028, "ph": "X", "name": "HashOfFile", "args": { "durationMS": 0.5547000169754028, "detail": "C:\\Program Files\\Unity\\Hub\\Editor\\2021.1.16f1\\Editor\\Data\\il2cpp\\external\\bdwgc\\os_dep.c" } },
{ "pid": 1, "tid": 72, "ts": 388859.5886230469, "dur": 386.2999975681305, "ph": "X", "name": "HashOfFile", "args": { "durationMS": 0.3862999975681305, "detail": "C:\\Program Files\\Unity\\Hub\\Editor\\2021.1.16f1\\Editor\\Data\\il2cpp\\external\\bdwgc\\win32_threads.c" } },
{ "pid": 1, "tid": 75, "ph": "M", "name": "thread_name", "args": { "name": "" } },
{ "pid": 1, "tid": 75, "ts": 390343.2922363281, "dur": 764.5999789237976, "ph": "X", "name": "HashOfFile", "args": { "durationMS": 0.7645999789237976, "detail": "C:\\Program Files\\Unity\\Hub\\Editor\\2021.1.16f1\\Editor\\Data\\il2cpp\\libil2cpp\\icalls\\mscorlib\\System.Runtime.Remoting.Contexts\\Context.cpp" } },
{ "pid": 1, "tid": 75, "ts": 393567.68798828125, "dur": 402.5999903678894, "ph": "X", "name": "HashOfFile", "args": { "durationMS": 0.4025999903678894, "detail": "C:\\Program Files\\Unity\\Hub\\Editor\\2021.1.16f1\\Editor\\Data\\il2cpp\\libil2cpp\\icalls\\mscorlib\\System\\Number.cpp" } },
{ "pid": 1, "tid": 75, "ts": 395123.59619140625, "dur": 384.799987077713, "ph": "X", "name": "HashOfFile", "args": { "durationMS": 0.384799987077713, "detail": "C:\\Program Files\\Unity\\Hub\\Editor\\2021.1.16f1\\Editor\\Data\\il2cpp\\libil2cpp\\icalls\\mscorlib\\System\\ValueType.cpp" } },
{ "pid": 1, "tid": 76, "ph": "M", "name": "thread_name", "args": { "name": "" } },
{ "pid": 1, "tid": 76, "ts": 388434.6923828125, "dur": 723.1000065803528, "ph": "X", "name": "HashOfFile", "args": { "durationMS": 0.7231000065803528, "detail": "C:\\Program Files\\Unity\\Hub\\Editor\\2021.1.16f1\\Editor\\Data\\il2cpp\\libil2cpp\\icalls\\mscorlib\\System.IO\\Path.cpp" } },
{ "pid": 1, "tid": 76, "ts": 391002.1057128906, "dur": 855.3000092506409, "ph": "X", "name": "HashOfFile", "args": { "durationMS": 0.8553000092506409, "detail": "C:\\Program Files\\Unity\\Hub\\Editor\\2021.1.16f1\\Editor\\Data\\il2cpp\\libil2cpp\\icalls\\mscorlib\\System.Security.Principal\\WindowsPrincipal.cpp" } },
{ "pid": 1, "tid": 76, "ts": 392627.8991699219, "dur": 1096.60005569458, "ph": "X", "name": "HashOfFile", "args": { "durationMS": 1.09660005569458, "detail": "C:\\Program Files\\Unity\\Hub\\Editor\\2021.1.16f1\\Editor\\Data\\il2cpp\\libil2cpp\\icalls\\mscorlib\\System\\Decimal.cpp" } },
{ "pid": 1, "tid": 76, "ts": 393842.3156738281, "dur": 911.0999703407288, "ph": "X", "name": "HashOfFile", "args": { "durationMS": 0.9110999703407288, "detail": "C:\\Program Files\\Unity\\Hub\\Editor\\2021.1.16f1\\Editor\\Data\\il2cpp\\libil2cpp\\icalls\\mscorlib\\System\\Object.cpp" } },
{ "pid": 1, "tid": 76, "ts": 394754.39453125, "dur": 831.2000036239624, "ph": "X", "name": "HashOfFile", "args": { "durationMS": 0.8312000036239624, "detail": "C:\\Program Files\\Unity\\Hub\\Editor\\2021.1.16f1\\Editor\\Data\\il2cpp\\libil2cpp\\icalls\\mscorlib\\System\\Type.cpp" } },
{ "pid": 1, "tid": 77, "ph": "M", "name": "thread_name", "args": { "name": "" } },
{ "pid": 1, "tid": 77, "ts": 390677.3986816406, "dur": 382.8999996185303, "ph": "X", "name": "HashOfFile", "args": { "durationMS": 0.3828999996185303, "detail": "C:\\Program Files\\Unity\\Hub\\Editor\\2021.1.16f1\\Editor\\Data\\il2cpp\\libil2cpp\\os\\Messages.cpp" } },
{ "pid": 1, "tid": 77, "ts": 391651.30615234375, "dur": 1522.6999521255493, "ph": "X", "name": "HashOfFile", "args": { "durationMS": 1.5226999521255493, "detail": "C:\\Program Files\\Unity\\Hub\\Editor\\2021.1.16f1\\Editor\\Data\\il2cpp\\libil2cpp\\os\\Posix\\MarshalAlloc.cpp" } },
{ "pid": 1, "tid": 95, "ph": "M", "name": "thread_name", "args": { "name": "" } },
{ "pid": 1, "tid": 95, "ts": 599331.9702148438, "dur": 24649.999618530273, "ph": "X", "name": "HashCompilerInvocation", "args": { "durationMS": 24.649999618530273, "detail": "Generics4.cpp" } },
{ "pid": 1, "tid": 95, "ts": 624146.6064453125, "dur": 10884.099960327148, "ph": "X", "name": "HashCompilerInvocation", "args": { "durationMS": 10.884099960327148, "detail": "mscorlib_CodeGen.c" } },
{ "pid": 1, "tid": 95, "ts": 635059.2041015625, "dur": 12917.200088500977, "ph": "X", "name": "HashCompilerInvocation", "args": { "durationMS": 12.917200088500977, "detail": "Il2CppTypeDefinitions.c" } },
{ "pid": 1, "tid": 95, "ts": 648002.3803710938, "dur": 11171.40007019043, "ph": "X", "name": "HashCompilerInvocation", "args": { "durationMS": 11.17140007019043, "detail": "mscorlib13.cpp" } },
{ "pid": 1, "tid": 95, "ts": 659199.70703125, "dur": 11545.900344848633, "ph": "X", "name": "HashCompilerInvocation", "args": { "durationMS": 11.545900344848633, "detail": "UnityEngine.CoreModule.cpp" } },
{ "pid": 1, "tid": 95, "ts": 670784.912109375, "dur": 10157.19985961914, "ph": "X", "name": "HashCompilerInvocation", "args": { "durationMS": 10.15719985961914, "detail": "mscorlib6.cpp" } },
{ "pid": 1, "tid": 95, "ts": 680967.4682617188, "dur": 8829.700469970703, "ph": "X", "name": "HashCompilerInvocation", "args": { "durationMS": 8.829700469970703, "detail": "mscorlib5.cpp" } },
{ "pid": 1, "tid": 95, "ts": 689821.2890625, "dur": 7873.099803924561, "ph": "X", "name": "HashCompilerInvocation", "args": { "durationMS": 7.8730998039245605, "detail": "mscorlib8.cpp" } },
{ "pid": 1, "tid": 95, "ts": 697718.8720703125, "dur": 8198.90022277832, "ph": "X", "name": "HashCompilerInvocation", "args": { "durationMS": 8.19890022277832, "detail": "GenericMethods.cpp" } },
{ "pid": 1, "tid": 95, "ts": 705945.6176757812, "dur": 6845.300197601318, "ph": "X", "name": "HashCompilerInvocation", "args": { "durationMS": 6.845300197601318, "detail": "mscorlib3.cpp" } },
{ "pid": 1, "tid": 95, "ts": 712822.2045898438, "dur": 7455.50012588501, "ph": "X", "name": "HashCompilerInvocation", "args": { "durationMS": 7.45550012588501, "detail": "UnityEngine.UI1.cpp" } },
{ "pid": 1, "tid": 95, "ts": 720305.908203125, "dur": 6287.0001792907715, "ph": "X", "name": "HashCompilerInvocation", "args": { "durationMS": 6.2870001792907715, "detail": "Generics5.cpp" } },
{ "pid": 1, "tid": 95, "ts": 726616.2109375, "dur": 6284.800052642822, "ph": "X", "name": "HashCompilerInvocation", "args": { "durationMS": 6.284800052642822, "detail": "UnityEngine.AndroidJNIModule.cpp" } },
{ "pid": 1, "tid": 95, "ts": 732923.7060546875, "dur": 6227.200031280518, "ph": "X", "name": "HashCompilerInvocation", "args": { "durationMS": 6.227200031280518, "detail": "Il2CppGenericInstDefinitions.c" } },
{ "pid": 1, "tid": 95, "ts": 739177.5512695312, "dur": 7554.900169372559, "ph": "X", "name": "HashCompilerInvocation", "args": { "durationMS": 7.554900169372559, "detail": "UnityEngine.UIElementsModule_Attr.cpp" } },
{ "pid": 1, "tid": 95, "ts": 746757.2021484375, "dur": 7271.900177001953, "ph": "X", "name": "HashCompilerInvocation", "args": { "durationMS": 7.271900177001953, "detail": "UnityEngine.AnimationModule.cpp" } },
{ "pid": 1, "tid": 95, "ts": 754053.8940429688, "dur": 6159.299850463867, "ph": "X", "name": "HashCompilerInvocation", "args": { "durationMS": 6.159299850463867, "detail": "UnityEngine.IMGUIModule_Attr.cpp" } },
{ "pid": 1, "tid": 95, "ts": 760243.5302734375, "dur": 5646.399974822998, "ph": "X", "name": "HashCompilerInvocation", "args": { "durationMS": 5.646399974822998, "detail": "Il2CppGenericMethodDefinitions.c" } },
{ "pid": 1, "tid": 95, "ts": 765914.4287109375, "dur": 5667.300224304199, "ph": "X", "name": "HashCompilerInvocation", "args": { "durationMS": 5.667300224304199, "detail": "GenericMethods3.cpp" } },
{ "pid": 1, "tid": 95, "ts": 771604.98046875, "dur": 7427.4001121521, "ph": "X", "name": "HashCompilerInvocation", "args": { "durationMS": 7.4274001121521, "detail": "UnityEngine.SharedInternalsModule_Attr.cpp" } },
{ "pid": 1, "tid": 95, "ts": 779056.4575195312, "dur": 6221.099853515625, "ph": "X", "name": "HashCompilerInvocation", "args": { "durationMS": 6.221099853515625, "detail": "UnityEngine.AudioModule_Attr.cpp" } },
{ "pid": 1, "tid": 95, "ts": 785300.048828125, "dur": 5689.400196075439, "ph": "X", "name": "HashCompilerInvocation", "args": { "durationMS": 5.6894001960754395, "detail": "UnityEngine.TextRenderingModule_Attr.cpp" } },
{ "pid": 1, "tid": 95, "ts": 791074.21875, "dur": 8024.200439453125, "ph": "X", "name": "HashCompilerInvocation", "args": { "durationMS": 8.024200439453125, "detail": "UnityEngine.GridModule_Attr.cpp" } },
{ "pid": 1, "tid": 95, "ts": 799143.798828125, "dur": 7643.199920654297, "ph": "X", "name": "HashCompilerInvocation", "args": { "durationMS": 7.643199920654297, "detail": "System_Attr.cpp" } },
{ "pid": 1, "tid": 95, "ts": 806806.0302734375, "dur": 6290.200233459473, "ph": "X", "name": "HashCompilerInvocation", "args": { "durationMS": 6.290200233459473, "detail": "UnityEngine.IMGUIModule_CodeGen.c" } },
{ "pid": 1, "tid": 95, "ts": 813119.5678710938, "dur": 4364.799976348877, "ph": "X", "name": "HashCompilerInvocation", "args": { "durationMS": 4.364799976348877, "detail": "System.Configuration.cpp" } },
{ "pid": 1, "tid": 95, "ts": 817502.9907226562, "dur": 5181.49995803833, "ph": "X", "name": "HashCompilerInvocation", "args": { "durationMS": 5.18149995803833, "detail": "UnityEngine.PhysicsModule.cpp" } },
{ "pid": 1, "tid": 95, "ts": 822701.1108398438, "dur": 5572.89981842041, "ph": "X", "name": "HashCompilerInvocation", "args": { "durationMS": 5.57289981842041, "detail": "UnityEngine.Physics2DModule_CodeGen.c" } },
{ "pid": 1, "tid": 95, "ts": 828293.212890625, "dur": 1216.3000106811523, "ph": "X", "name": "HashCompilerInvocation", "args": { "durationMS": 1.2163000106811523, "detail": "Assembly-CSharp_CodeGen.c" } },
{ "pid": 1, "tid": 95, "ts": 829525.3295898438, "dur": 5757.199764251709, "ph": "X", "name": "HashCompilerInvocation", "args": { "durationMS": 5.757199764251709, "detail": "UnityEngine.SharedInternalsModule_CodeGen.c" } },
{ "pid": 1, "tid": 95, "ts": 835305.1147460938, "dur": 6000.500202178955, "ph": "X", "name": "HashCompilerInvocation", "args": { "durationMS": 6.000500202178955, "detail": "UnityEngine.UIElementsNativeModule_CodeGen.c" } },
{ "pid": 1, "tid": 95, "ts": 841327.0263671875, "dur": 1089.5999670028687, "ph": "X", "name": "HashCompilerInvocation", "args": { "durationMS": 1.0895999670028687, "detail": "zutil.c" } },
{ "pid": 1, "tid": 95, "ts": 842432.0068359375, "dur": 7477.499961853027, "ph": "X", "name": "HashCompilerInvocation", "args": { "durationMS": 7.477499961853027, "detail": "UnityEngine.GridModule.cpp" } },
{ "pid": 1, "tid": 95, "ts": 849927.001953125, "dur": 5544.400215148926, "ph": "X", "name": "HashCompilerInvocation", "args": { "durationMS": 5.544400215148926, "detail": "UnityEngine.SpriteShapeModule.cpp" } },
{ "pid": 1, "tid": 95, "ts": 855489.6850585938, "dur": 6896.599769592285, "ph": "X", "name": "HashCompilerInvocation", "args": { "durationMS": 6.896599769592285, "detail": "Lump_libil2cpp_metadata.cpp" } },
{ "pid": 1, "tid": 95, "ts": 862408.6303710938, "dur": 6729.400157928467, "ph": "X", "name": "HashCompilerInvocation", "args": { "durationMS": 6.729400157928467, "detail": "System.Xml_CodeGen.c" } },
{ "pid": 1, "tid": 95, "ts": 869158.69140625, "dur": 1274.7000455856323, "ph": "X", "name": "HashCompilerInvocation", "args": { "durationMS": 1.2747000455856323, "detail": "gzclose.c" } },
{ "pid": 1, "tid": 95, "ts": 870454.58984375, "dur": 4639.2998695373535, "ph": "X", "name": "HashCompilerInvocation", "args": { "durationMS": 4.6392998695373535, "detail": "UnityEngine.SpriteShapeModule_CodeGen.c" } },
{ "pid": 1, "tid": 95, "ts": 875111.4501953125, "dur": 6514.599800109863, "ph": "X", "name": "HashCompilerInvocation", "args": { "durationMS": 6.514599800109863, "detail": "Il2CppGenericComDefinitions1.cpp" } },
{ "pid": 1, "tid": 95, "ts": 881645.1416015625, "dur": 7484.099864959717, "ph": "X", "name": "HashCompilerInvocation", "args": { "durationMS": 7.484099864959717, "detail": "Il2CppGenericComDefinitions4.cpp" } },
{ "pid": 1, "tid": 95, "ts": 889147.8881835938, "dur": 7256.999969482422, "ph": "X", "name": "HashCompilerInvocation", "args": { "durationMS": 7.256999969482422, "detail": "Il2CppGenericComDefinitions8.cpp" } },
{ "pid": 1, "tid": 95, "ts": 896428.3447265625, "dur": 7331.500053405762, "ph": "X", "name": "HashCompilerInvocation", "args": { "durationMS": 7.331500053405762, "detail": "Il2CppGenericComDefinitions13.cpp" } },
{ "pid": 1, "tid": 95, "ts": 903779.4189453125, "dur": 3275.7999897003174, "ph": "X", "name": "HashCompilerInvocation", "args": { "durationMS": 3.2757999897003174, "detail": "Il2CppGenericComDefinitions17.cpp" } },
{ "pid": 1, "tid": 95, "ts": 907083.1909179688, "dur": 24797.100067138672, "ph": "X", "name": "HashCompilerInvocation", "args": { "durationMS": 24.797100067138672, "detail": "Il2CppGenericComDefinitions20.cpp" } },
{ "pid": 1, "tid": 95, "ts": 931914.6728515625, "dur": 8612.40005493164, "ph": "X", "name": "HashCompilerInvocation", "args": { "durationMS": 8.61240005493164, "detail": "Lump_libil2cpp_debugger.cpp" } },
{ "pid": 1, "tid": 93, "ph": "M", "name": "thread_name", "args": { "name": "" } },
{ "pid": 1, "tid": 93, "ts": 599350.8911132812, "dur": 33686.302185058594, "ph": "X", "name": "HashCompilerInvocation", "args": { "durationMS": 33.686302185058594, "detail": "Il2CppCCalculateFieldValues.cpp" } },
{ "pid": 1, "tid": 93, "ts": 633062.5, "dur": 11308.699607849121, "ph": "X", "name": "HashCompilerInvocation", "args": { "durationMS": 11.308699607849121, "detail": "UnityEngine.UI.cpp" } },
{ "pid": 1, "tid": 93, "ts": 644406.5551757812, "dur": 14219.29931640625, "ph": "X", "name": "HashCompilerInvocation", "args": { "durationMS": 14.21929931640625, "detail": "mscorlib10.cpp" } },
{ "pid": 1, "tid": 93, "ts": 658654.2358398438, "dur": 11358.30020904541, "ph": "X", "name": "HashCompilerInvocation", "args": { "durationMS": 11.35830020904541, "detail": "GenericMethods2.cpp" } },
{ "pid": 1, "tid": 93, "ts": 670042.4194335938, "dur": 8939.800262451172, "ph": "X", "name": "HashCompilerInvocation", "args": { "durationMS": 8.939800262451172, "detail": "mscorlib7.cpp" } },
{ "pid": 1, "tid": 93, "ts": 679079.4067382812, "dur": 8772.100448608398, "ph": "X", "name": "HashCompilerInvocation", "args": { "durationMS": 8.772100448608398, "detail": "Generics7.cpp" } },
{ "pid": 1, "tid": 93, "ts": 687879.2114257812, "dur": 7363.699913024902, "ph": "X", "name": "HashCompilerInvocation", "args": { "durationMS": 7.363699913024902, "detail": "mscorlib15.cpp" } },
{ "pid": 1, "tid": 93, "ts": 695269.3481445312, "dur": 8060.199737548828, "ph": "X", "name": "HashCompilerInvocation", "args": { "durationMS": 8.060199737548828, "detail": "mscorlib14.cpp" } },
{ "pid": 1, "tid": 93, "ts": 703357.6049804688, "dur": 7343.200206756592, "ph": "X", "name": "HashCompilerInvocation", "args": { "durationMS": 7.343200206756592, "detail": "mscorlib12.cpp" } },
{ "pid": 1, "tid": 93, "ts": 710725.4638671875, "dur": 8688.09986114502, "ph": "X", "name": "HashCompilerInvocation", "args": { "durationMS": 8.68809986114502, "detail": "Generics6.cpp" } },
{ "pid": 1, "tid": 93, "ts": 719436.4013671875, "dur": 6441.400051116943, "ph": "X", "name": "HashCompilerInvocation", "args": { "durationMS": 6.441400051116943, "detail": "System.cpp" } },
{ "pid": 1, "tid": 93, "ts": 725898.6206054688, "dur": 5943.79997253418, "ph": "X", "name": "HashCompilerInvocation", "args": { "durationMS": 5.94379997253418, "detail": "UnityEngine.IMGUIModule.cpp" } },
{ "pid": 1, "tid": 93, "ts": 731864.8071289062, "dur": 5943.900108337402, "ph": "X", "name": "HashCompilerInvocation", "args": { "durationMS": 5.943900108337402, "detail": "UnityEngine.UI_CodeGen.c" } },
{ "pid": 1, "tid": 93, "ts": 737830.322265625, "dur": 2746.299982070923, "ph": "X", "name": "HashCompilerInvocation", "args": { "durationMS": 2.746299982070923, "detail": "Assembly-CSharp.cpp" } },
{ "pid": 1, "tid": 93, "ts": 740600.8911132812, "dur": 6999.199867248535, "ph": "X", "name": "HashCompilerInvocation", "args": { "durationMS": 6.999199867248535, "detail": "UnityEngine.UIElementsModule_CodeGen.c" } },
{ "pid": 1, "tid": 93, "ts": 747624.3896484375, "dur": 7209.59997177124, "ph": "X", "name": "HashCompilerInvocation", "args": { "durationMS": 7.20959997177124, "detail": "UnityEngine.UIModule.cpp" } },
{ "pid": 1, "tid": 93, "ts": 754857.7880859375, "dur": 8403.10001373291, "ph": "X", "name": "HashCompilerInvocation", "args": { "durationMS": 8.40310001373291, "detail": "UnityEngine.Physics2DModule.cpp" } },
{ "pid": 1, "tid": 93, "ts": 763284.66796875, "dur": 7218.599796295166, "ph": "X", "name": "HashCompilerInvocation", "args": { "durationMS": 7.218599796295166, "detail": "UnityEngine.SharedInternalsModule.cpp" } },
{ "pid": 1, "tid": 93, "ts": 770527.099609375, "dur": 6506.999969482422, "ph": "X", "name": "HashCompilerInvocation", "args": { "durationMS": 6.506999969482422, "detail": "UnityEngine.InputLegacyModule.cpp" } },
{ "pid": 1, "tid": 93, "ts": 777058.837890625, "dur": 7089.200019836426, "ph": "X", "name": "HashCompilerInvocation", "args": { "durationMS": 7.089200019836426, "detail": "UnityEngine.UIElementsNativeModule.cpp" } },
{ "pid": 1, "tid": 93, "ts": 784172.1801757812, "dur": 5953.89986038208, "ph": "X", "name": "HashCompilerInvocation", "args": { "durationMS": 5.95389986038208, "detail": "UnityEngine.TilemapModule_Attr.cpp" } },
{ "pid": 1, "tid": 93, "ts": 790425.1098632812, "dur": 9279.999732971191, "ph": "X", "name": "HashCompilerInvocation", "args": { "durationMS": 9.279999732971191, "detail": "Il2CppRgctxTable.c" } },
{ "pid": 1, "tid": 93, "ts": 799736.0229492188, "dur": 7398.799896240234, "ph": "X", "name": "HashCompilerInvocation", "args": { "durationMS": 7.398799896240234, "detail": "UnityEngine.AudioModule.cpp" } },
{ "pid": 1, "tid": 93, "ts": 807152.8930664062, "dur": 6751.399993896484, "ph": "X", "name": "HashCompilerInvocation", "args": { "durationMS": 6.751399993896484, "detail": "System.Core_Attr.cpp" } },
{ "pid": 1, "tid": 93, "ts": 813922.607421875, "dur": 6697.700023651123, "ph": "X", "name": "HashCompilerInvocation", "args": { "durationMS": 6.697700023651123, "detail": "System.Configuration_Attr.cpp" } },
{ "pid": 1, "tid": 93, "ts": 820638.7939453125, "dur": 1065.500020980835, "ph": "X", "name": "HashCompilerInvocation", "args": { "durationMS": 1.065500020980835, "detail": "xamarin_getifaddrs.c" } },
{ "pid": 1, "tid": 93, "ts": 821723.2055664062, "dur": 5700.699806213379, "ph": "X", "name": "HashCompilerInvocation", "args": { "durationMS": 5.700699806213379, "detail": "UnityEngine.AnimationModule_CodeGen.c" } },
{ "pid": 1, "tid": 93, "ts": 827442.0166015625, "dur": 1086.7999792099, "ph": "X", "name": "HashCompilerInvocation", "args": { "durationMS": 1.0867999792099, "detail": "gzread.c" } },
{ "pid": 1, "tid": 93, "ts": 828551.2084960938, "dur": 1149.6000289916992, "ph": "X", "name": "HashCompilerInvocation", "args": { "durationMS": 1.1496000289916992, "detail": "gzwrite.c" } },
{ "pid": 1, "tid": 93, "ts": 829718.8720703125, "dur": 937.7999901771545, "ph": "X", "name": "HashCompilerInvocation", "args": { "durationMS": 0.9377999901771545, "detail": "gzlib.c" } },
{ "pid": 1, "tid": 93, "ts": 830672.9736328125, "dur": 1058.899998664856, "ph": "X", "name": "HashCompilerInvocation", "args": { "durationMS": 1.058899998664856, "detail": "crc32.c" } },
{ "pid": 1, "tid": 93, "ts": 831749.8779296875, "dur": 4662.600040435791, "ph": "X", "name": "HashCompilerInvocation", "args": { "durationMS": 4.662600040435791, "detail": "UnityEngine.InputLegacyModule_CodeGen.c" } },
{ "pid": 1, "tid": 93, "ts": 836430.2978515625, "dur": 6254.499912261963, "ph": "X", "name": "HashCompilerInvocation", "args": { "durationMS": 6.254499912261963, "detail": "UnityEngine.AudioModule_CodeGen.c" } },
{ "pid": 1, "tid": 93, "ts": 842701.904296875, "dur": 7244.699954986572, "ph": "X", "name": "HashCompilerInvocation", "args": { "durationMS": 7.244699954986572, "detail": "Lump_libil2cpp_vm.cpp" } },
{ "pid": 1, "tid": 93, "ts": 849964.7827148438, "dur": 5490.699768066406, "ph": "X", "name": "HashCompilerInvocation", "args": { "durationMS": 5.490699768066406, "detail": "Il2CppCodeRegistration.cpp" } },
{ "pid": 1, "tid": 93, "ts": 855472.5952148438, "dur": 6120.100021362305, "ph": "X", "name": "HashCompilerInvocation", "args": { "durationMS": 6.120100021362305, "detail": "Il2CppReversePInvokeWrapperTable.cpp" } },
{ "pid": 1, "tid": 93, "ts": 861609.4970703125, "dur": 6286.6997718811035, "ph": "X", "name": "HashCompilerInvocation", "args": { "durationMS": 6.2866997718811035, "detail": "UnityEngine.GridModule_CodeGen.c" } },
{ "pid": 1, "tid": 93, "ts": 867914.0625, "dur": 3509.999990463257, "ph": "X", "name": "HashCompilerInvocation", "args": { "durationMS": 3.509999990463257, "detail": "Lump_libil2cpp_mono.cpp" } },
{ "pid": 1, "tid": 93, "ts": 871441.2841796875, "dur": 6133.200168609619, "ph": "X", "name": "HashCompilerInvocation", "args": { "durationMS": 6.133200168609619, "detail": "UnityEngine_CodeGen.c" } },
{ "pid": 1, "tid": 93, "ts": 877593.3837890625, "dur": 4832.499980926514, "ph": "X", "name": "HashCompilerInvocation", "args": { "durationMS": 4.832499980926514, "detail": "Il2CppGenericComDefinitions2.cpp" } },
{ "pid": 1, "tid": 93, "ts": 882445.4345703125, "dur": 6755.40018081665, "ph": "X", "name": "HashCompilerInvocation", "args": { "durationMS": 6.75540018081665, "detail": "Il2CppGenericComDefinitions7.cpp" } },
{ "pid": 1, "tid": 93, "ts": 889218.6889648438, "dur": 7920.000076293945, "ph": "X", "name": "HashCompilerInvocation", "args": { "durationMS": 7.920000076293945, "detail": "Il2CppGenericComDefinitions10.cpp" } },
{ "pid": 1, "tid": 93, "ts": 897155.7006835938, "dur": 7396.699905395508, "ph": "X", "name": "HashCompilerInvocation", "args": { "durationMS": 7.396699905395508, "detail": "Il2CppGenericComDefinitions16.cpp" } },
{ "pid": 1, "tid": 93, "ts": 904570.6787109375, "dur": 26937.999725341797, "ph": "X", "name": "HashCompilerInvocation", "args": { "durationMS": 26.937999725341797, "detail": "Il2CppGenericComDefinitions19.cpp" } },
{ "pid": 1, "tid": 93, "ts": 931553.1005859375, "dur": 8840.499877929688, "ph": "X", "name": "HashCompilerInvocation", "args": { "durationMS": 8.840499877929688, "detail": "Il2CppGenericComDefinitions21.cpp" } },
{ "pid": 1, "tid": 96, "ph": "M", "name": "thread_name", "args": { "name": "" } },
{ "pid": 1, "tid": 96, "ts": 599352.9052734375, "dur": 23562.700271606445, "ph": "X", "name": "HashCompilerInvocation", "args": { "durationMS": 23.562700271606445, "detail": "Generics2.cpp" } },
{ "pid": 1, "tid": 96, "ts": 623388.18359375, "dur": 11559.399604797363, "ph": "X", "name": "HashCompilerInvocation", "args": { "durationMS": 11.559399604797363, "detail": "UnityEngine.UIElementsModule.cpp" } },
{ "pid": 1, "tid": 96, "ts": 634970.3979492188, "dur": 12426.199913024902, "ph": "X", "name": "HashCompilerInvocation", "args": { "durationMS": 12.426199913024902, "detail": "mscorlib9.cpp" } },
{ "pid": 1, "tid": 96, "ts": 647424.31640625, "dur": 11834.89990234375, "ph": "X", "name": "HashCompilerInvocation", "args": { "durationMS": 11.83489990234375, "detail": "mscorlib1.cpp" } },
{ "pid": 1, "tid": 96, "ts": 659283.8134765625, "dur": 11598.299980163574, "ph": "X", "name": "HashCompilerInvocation", "args": { "durationMS": 11.598299980163574, "detail": "GenericMethods1.cpp" } },
{ "pid": 1, "tid": 96, "ts": 670905.7006835938, "dur": 11274.999618530273, "ph": "X", "name": "HashCompilerInvocation", "args": { "durationMS": 11.274999618530273, "detail": "mscorlib16.cpp" } },
{ "pid": 1, "tid": 96, "ts": 682205.56640625, "dur": 9307.39974975586, "ph": "X", "name": "HashCompilerInvocation", "args": { "durationMS": 9.30739974975586, "detail": "Generics1.cpp" } },
{ "pid": 1, "tid": 96, "ts": 691535.9497070312, "dur": 8656.599998474121, "ph": "X", "name": "HashCompilerInvocation", "args": { "durationMS": 8.656599998474121, "detail": "UnityEngine.UIElementsModule1.cpp" } },
{ "pid": 1, "tid": 96, "ts": 700216.552734375, "dur": 8920.499801635742, "ph": "X", "name": "HashCompilerInvocation", "args": { "durationMS": 8.920499801635742, "detail": "UnityEngine.UI3.cpp" } },
{ "pid": 1, "tid": 96, "ts": 709162.7807617188, "dur": 9722.100257873535, "ph": "X", "name": "HashCompilerInvocation", "args": { "durationMS": 9.722100257873535, "detail": "Il2CppGenericMethodPointerTable.cpp" } },
{ "pid": 1, "tid": 96, "ts": 718909.1796875, "dur": 4581.399917602539, "ph": "X", "name": "HashCompilerInvocation", "args": { "durationMS": 4.581399917602539, "detail": "Il2CppMetadataUsage.c" } },
{ "pid": 1, "tid": 96, "ts": 723513.916015625, "dur": 5011.70015335083, "ph": "X", "name": "HashCompilerInvocation", "args": { "durationMS": 5.01170015335083, "detail": "UnityEngine.CoreModule_Attr.cpp" } },
{ "pid": 1, "tid": 96, "ts": 728557.8002929688, "dur": 5768.400192260742, "ph": "X", "name": "HashCompilerInvocation", "args": { "durationMS": 5.768400192260742, "detail": "mscorlib_Attr.cpp" } },
{ "pid": 1, "tid": 96, "ts": 734349.609375, "dur": 5252.999782562256, "ph": "X", "name": "HashCompilerInvocation", "args": { "durationMS": 5.252999782562256, "detail": "UnityEngine.CoreModule_CodeGen.c" } },
{ "pid": 1, "tid": 96, "ts": 739626.2817382812, "dur": 6802.10018157959, "ph": "X", "name": "HashCompilerInvocation", "args": { "durationMS": 6.80210018157959, "detail": "UnresolvedVirtualCallStubs.cpp" } },
{ "pid": 1, "tid": 96, "ts": 746460.5102539062, "dur": 7082.399845123291, "ph": "X", "name": "HashCompilerInvocation", "args": { "durationMS": 7.082399845123291, "detail": "Il2CppCCTypeValuesTable.cpp" } },
{ "pid": 1, "tid": 96, "ts": 753568.9086914062, "dur": 4965.700149536133, "ph": "X", "name": "HashCompilerInvocation", "args": { "durationMS": 4.965700149536133, "detail": "Il2CppGenericMethodTable.c" } },
{ "pid": 1, "tid": 96, "ts": 758565.0024414062, "dur": 5347.599983215332, "ph": "X", "name": "HashCompilerInvocation", "args": { "durationMS": 5.347599983215332, "detail": "Il2CppGenericClassTable.c" } },
{ "pid": 1, "tid": 96, "ts": 763935.4858398438, "dur": 6162.199974060059, "ph": "X", "name": "HashCompilerInvocation", "args": { "durationMS": 6.162199974060059, "detail": "UnityEngine.AnimationModule_Attr.cpp" } },
{ "pid": 1, "tid": 96, "ts": 770122.3754882812, "dur": 6911.900043487549, "ph": "X", "name": "HashCompilerInvocation", "args": { "durationMS": 6.911900043487549, "detail": "Il2CppInteropDataTable.cpp" } },
{ "pid": 1, "tid": 96, "ts": 777058.4106445312, "dur": 7112.99991607666, "ph": "X", "name": "HashCompilerInvocation", "args": { "durationMS": 7.11299991607666, "detail": "Il2CppCCFieldValuesTable.cpp" } },
{ "pid": 1, "tid": 96, "ts": 784195.1293945312, "dur": 6169.7998046875, "ph": "X", "name": "HashCompilerInvocation", "args": { "durationMS": 6.1697998046875, "detail": "UnityEngine.AndroidJNIModule_CodeGen.c" } },
{ "pid": 1, "tid": 96, "ts": 790554.443359375, "dur": 8432.600021362305, "ph": "X", "name": "HashCompilerInvocation", "args": { "durationMS": 8.432600021362305, "detail": "UnityEngine.PhysicsModule_Attr.cpp" } },
{ "pid": 1, "tid": 96, "ts": 799057.0068359375, "dur": 7056.600093841553, "ph": "X", "name": "HashCompilerInvocation", "args": { "durationMS": 7.056600093841553, "detail": "UnityEngine.InputLegacyModule_Attr.cpp" } },
{ "pid": 1, "tid": 96, "ts": 806138.671875, "dur": 1260.3000402450562, "ph": "X", "name": "HashCompilerInvocation", "args": { "durationMS": 1.2603000402450562, "detail": "deflate.c" } },
{ "pid": 1, "tid": 96, "ts": 807423.4619140625, "dur": 6697.89981842041, "ph": "X", "name": "HashCompilerInvocation", "args": { "durationMS": 6.69789981842041, "detail": "System.Core_CodeGen.c" } },
{ "pid": 1, "tid": 96, "ts": 814139.404296875, "dur": 1096.3000059127808, "ph": "X", "name": "HashCompilerInvocation", "args": { "durationMS": 1.0963000059127808, "detail": "trees.c" } },
{ "pid": 1, "tid": 96, "ts": 815259.0942382812, "dur": 1486.9999885559082, "ph": "X", "name": "HashCompilerInvocation", "args": { "durationMS": 1.4869999885559082, "detail": "il2cpp-api.cpp" } },
{ "pid": 1, "tid": 96, "ts": 816763.0004882812, "dur": 5480.299949645996, "ph": "X", "name": "HashCompilerInvocation", "args": { "durationMS": 5.480299949645996, "detail": "Mono.Security_Attr.cpp" } },
{ "pid": 1, "tid": 96, "ts": 822261.1694335938, "dur": 1022.5000381469727, "ph": "X", "name": "HashCompilerInvocation", "args": { "durationMS": 1.0225000381469727, "detail": "infback.c" } },
{ "pid": 1, "tid": 96, "ts": 823323.0590820312, "dur": 5265.2997970581055, "ph": "X", "name": "HashCompilerInvocation", "args": { "durationMS": 5.2652997970581055, "detail": "System.Core.cpp" } },
{ "pid": 1, "tid": 96, "ts": 828606.7504882812, "dur": 4932.499885559082, "ph": "X", "name": "HashCompilerInvocation", "args": { "durationMS": 4.932499885559082, "detail": "Lump_libil2cpp_icalls.cpp" } },
{ "pid": 1, "tid": 96, "ts": 833556.7626953125, "dur": 999.4000196456909, "ph": "X", "name": "HashCompilerInvocation", "args": { "durationMS": 0.9994000196456909, "detail": "inftrees.c" } },
{ "pid": 1, "tid": 96, "ts": 834581.787109375, "dur": 1065.500020980835, "ph": "X", "name": "HashCompilerInvocation", "args": { "durationMS": 1.065500020980835, "detail": "inffast.c" } },
{ "pid": 1, "tid": 96, "ts": 835663.5131835938, "dur": 6689.599990844727, "ph": "X", "name": "HashCompilerInvocation", "args": { "durationMS": 6.689599990844727, "detail": "UnityEngine.TilemapModule_CodeGen.c" } },
{ "pid": 1, "tid": 96, "ts": 842370.7275390625, "dur": 6198.500156402588, "ph": "X", "name": "HashCompilerInvocation", "args": { "durationMS": 6.198500156402588, "detail": "System.Xml.cpp" } },
{ "pid": 1, "tid": 96, "ts": 848587.7075195312, "dur": 1095.4999923706055, "ph": "X", "name": "HashCompilerInvocation", "args": { "durationMS": 1.0954999923706055, "detail": "adler32.c" } },
{ "pid": 1, "tid": 96, "ts": 849720.703125, "dur": 4872.099876403809, "ph": "X", "name": "HashCompilerInvocation", "args": { "durationMS": 4.872099876403809, "detail": "Mono.Security_CodeGen.c" } },
{ "pid": 1, "tid": 96, "ts": 854609.7412109375, "dur": 3181.2000274658203, "ph": "X", "name": "HashCompilerInvocation", "args": { "durationMS": 3.1812000274658203, "detail": "UnityEngine.PhysicsModule_CodeGen.c" } },
{ "pid": 1, "tid": 96, "ts": 857809.08203125, "dur": 1064.3999576568604, "ph": "X", "name": "HashCompilerInvocation", "args": { "durationMS": 1.0643999576568604, "detail": "UnityAdsStubs.cpp" } },
{ "pid": 1, "tid": 96, "ts": 858894.7143554688, "dur": 736.299991607666, "ph": "X", "name": "HashCompilerInvocation", "args": { "durationMS": 0.736299991607666, "detail": "krait_signal_handler.c" } },
{ "pid": 1, "tid": 96, "ts": 859648.92578125, "dur": 4892.199993133545, "ph": "X", "name": "HashCompilerInvocation", "args": { "durationMS": 4.892199993133545, "detail": "Il2CppMetadataRegistration.c" } },
{ "pid": 1, "tid": 96, "ts": 864558.7768554688, "dur": 5650.8002281188965, "ph": "X", "name": "HashCompilerInvocation", "args": { "durationMS": 5.6508002281188965, "detail": "UnityEngine.cpp" } },
{ "pid": 1, "tid": 96, "ts": 870227.1728515625, "dur": 1198.3000040054321, "ph": "X", "name": "HashCompilerInvocation", "args": { "durationMS": 1.1983000040054321, "detail": "il2cpp-benchmark-support.cpp" } },
{ "pid": 1, "tid": 96, "ts": 871442.626953125, "dur": 10468.700408935547, "ph": "X", "name": "HashCompilerInvocation", "args": { "durationMS": 10.468700408935547, "detail": "Lump_libil2cpp_codegen.cpp" } },
{ "pid": 1, "tid": 96, "ts": 881928.5278320312, "dur": 7735.199928283691, "ph": "X", "name": "HashCompilerInvocation", "args": { "durationMS": 7.735199928283691, "detail": "Il2CppGenericComDefinitions5.cpp" } },
{ "pid": 1, "tid": 96, "ts": 889682.12890625, "dur": 7355.400085449219, "ph": "X", "name": "HashCompilerInvocation", "args": { "durationMS": 7.355400085449219, "detail": "Il2CppGenericComDefinitions12.cpp" } },
{ "pid": 1, "tid": 96, "ts": 897058.2275390625, "dur": 7415.299892425537, "ph": "X", "name": "HashCompilerInvocation", "args": { "durationMS": 7.415299892425537, "detail": "Il2CppGenericComDefinitions15.cpp" } },
{ "pid": 1, "tid": 96, "ts": 904490.1733398438, "dur": 27470.0984954834, "ph": "X", "name": "HashCompilerInvocation", "args": { "durationMS": 27.4700984954834, "detail": "Il2CppGenericComDefinitions9.cpp" } },
{ "pid": 1, "tid": 96, "ts": 931982.1166992188, "dur": 1638.100028038025, "ph": "X", "name": "HashCompilerInvocation", "args": { "durationMS": 1.638100028038025, "detail": "il2cpp-runtime-stats.cpp" } },
{ "pid": 1, "tid": 94, "ph": "M", "name": "thread_name", "args": { "name": "" } },
{ "pid": 1, "tid": 94, "ts": 599391.0522460938, "dur": 32476.200103759766, "ph": "X", "name": "HashCompilerInvocation", "args": { "durationMS": 32.476200103759766, "detail": "Il2CppCCalculateTypeValues.cpp" } },
{ "pid": 1, "tid": 94, "ts": 631900.87890625, "dur": 9724.699974060059, "ph": "X", "name": "HashCompilerInvocation", "args": { "durationMS": 9.724699974060059, "detail": "Il2CppInvokerTable.cpp" } },
{ "pid": 1, "tid": 94, "ts": 641651.611328125, "dur": 12679.200172424316, "ph": "X", "name": "HashCompilerInvocation", "args": { "durationMS": 12.679200172424316, "detail": "UnityEngine.UI2.cpp" } },
{ "pid": 1, "tid": 94, "ts": 654358.88671875, "dur": 8847.800254821777, "ph": "X", "name": "HashCompilerInvocation", "args": { "durationMS": 8.847800254821777, "detail": "mscorlib.cpp" } },
{ "pid": 1, "tid": 94, "ts": 663235.7788085938, "dur": 8757.100105285645, "ph": "X", "name": "HashCompilerInvocation", "args": { "durationMS": 8.757100105285645, "detail": "mscorlib4.cpp" } },
{ "pid": 1, "tid": 94, "ts": 672015.7470703125, "dur": 10599.300384521484, "ph": "X", "name": "HashCompilerInvocation", "args": { "durationMS": 10.599300384521484, "detail": "mscorlib2.cpp" } },
{ "pid": 1, "tid": 94, "ts": 682635.009765625, "dur": 9101.799964904785, "ph": "X", "name": "HashCompilerInvocation", "args": { "durationMS": 9.101799964904785, "detail": "Generics.cpp" } },
{ "pid": 1, "tid": 94, "ts": 691758.9111328125, "dur": 8599.599838256836, "ph": "X", "name": "HashCompilerInvocation", "args": { "durationMS": 8.599599838256836, "detail": "Generics3.cpp" } },
{ "pid": 1, "tid": 94, "ts": 700382.8125, "dur": 8924.400329589844, "ph": "X", "name": "HashCompilerInvocation", "args": { "durationMS": 8.924400329589844, "detail": "UnityEngine.CoreModule1.cpp" } },
{ "pid": 1, "tid": 94, "ts": 709334.9609375, "dur": 7677.800178527832, "ph": "X", "name": "HashCompilerInvocation", "args": { "durationMS": 7.677800178527832, "detail": "mscorlib11.cpp" } },
{ "pid": 1, "tid": 94, "ts": 717416.9921875, "dur": 6448.599815368652, "ph": "X", "name": "HashCompilerInvocation", "args": { "durationMS": 6.448599815368652, "detail": "System1.cpp" } },
{ "pid": 1, "tid": 94, "ts": 723890.2587890625, "dur": 5718.400001525879, "ph": "X", "name": "HashCompilerInvocation", "args": { "durationMS": 5.718400001525879, "detail": "Generics8.cpp" } },
{ "pid": 1, "tid": 94, "ts": 729632.2021484375, "dur": 5476.6998291015625, "ph": "X", "name": "HashCompilerInvocation", "args": { "durationMS": 5.4766998291015625, "detail": "System2.cpp" } },
{ "pid": 1, "tid": 94, "ts": 735130.7983398438, "dur": 2211.6000652313232, "ph": "X", "name": "HashCompilerInvocation", "args": { "durationMS": 2.2116000652313232, "detail": "char-conversions.cpp" } },
{ "pid": 1, "tid": 94, "ts": 737367.3095703125, "dur": 4236.599922180176, "ph": "X", "name": "HashCompilerInvocation", "args": { "durationMS": 4.236599922180176, "detail": "UnityEngine.UI_Attr.cpp" } },
{ "pid": 1, "tid": 94, "ts": 741626.0375976562, "dur": 5941.89977645874, "ph": "X", "name": "HashCompilerInvocation", "args": { "durationMS": 5.94189977645874, "detail": "Il2CppGenericAdjustorThunkTable.cpp" } },
{ "pid": 1, "tid": 94, "ts": 747590.6982421875, "dur": 7233.90007019043, "ph": "X", "name": "HashCompilerInvocation", "args": { "durationMS": 7.23390007019043, "detail": "UnityEngine.AndroidJNIModule_Attr.cpp" } },
{ "pid": 1, "tid": 94, "ts": 754848.6328125, "dur": 6515.500068664551, "ph": "X", "name": "HashCompilerInvocation", "args": { "durationMS": 6.515500068664551, "detail": "UnityEngine.TextRenderingModule.cpp" } },
{ "pid": 1, "tid": 94, "ts": 761387.20703125, "dur": 5994.900226593018, "ph": "X", "name": "HashCompilerInvocation", "args": { "durationMS": 5.994900226593018, "detail": "System_CodeGen.c" } },
{ "pid": 1, "tid": 94, "ts": 767405.7006835938, "dur": 5135.39981842041, "ph": "X", "name": "HashCompilerInvocation", "args": { "durationMS": 5.13539981842041, "detail": "UnityEngine.Physics2DModule_Attr.cpp" } },
{ "pid": 1, "tid": 94, "ts": 772559.08203125, "dur": 6095.200061798096, "ph": "X", "name": "HashCompilerInvocation", "args": { "durationMS": 6.095200061798096, "detail": "Mono.Security.cpp" } },
{ "pid": 1, "tid": 94, "ts": 778678.8940429688, "dur": 6400.899887084961, "ph": "X", "name": "HashCompilerInvocation", "args": { "durationMS": 6.400899887084961, "detail": "UnityEngine.UIModule_Attr.cpp" } },
{ "pid": 1, "tid": 94, "ts": 785102.7221679688, "dur": 7029.799938201904, "ph": "X", "name": "HashCompilerInvocation", "args": { "durationMS": 7.029799938201904, "detail": "UnityEngine.UIElementsNativeModule_Attr.cpp" } },
{ "pid": 1, "tid": 94, "ts": 792244.2626953125, "dur": 7501.200199127197, "ph": "X", "name": "HashCompilerInvocation", "args": { "durationMS": 7.501200199127197, "detail": "UnityEngine.TilemapModule.cpp" } },
{ "pid": 1, "tid": 94, "ts": 799768.5546875, "dur": 7416.800022125244, "ph": "X", "name": "HashCompilerInvocation", "args": { "durationMS": 7.416800022125244, "detail": "UnityEngine.SpriteShapeModule_Attr.cpp" } },
{ "pid": 1, "tid": 94, "ts": 807202.3315429688, "dur": 1051.4999628067017, "ph": "X", "name": "HashCompilerInvocation", "args": { "durationMS": 1.0514999628067017, "detail": "inflate.c" } },
{ "pid": 1, "tid": 94, "ts": 808268.9208984375, "dur": 6220.600128173828, "ph": "X", "name": "HashCompilerInvocation", "args": { "durationMS": 6.220600128173828, "detail": "System.Xml_Attr.cpp" } },
{ "pid": 1, "tid": 94, "ts": 814507.7514648438, "dur": 6530.300140380859, "ph": "X", "name": "HashCompilerInvocation", "args": { "durationMS": 6.530300140380859, "detail": "Assembly-CSharp_Attr.cpp" } },
{ "pid": 1, "tid": 94, "ts": 821055.6640625, "dur": 5375.29993057251, "ph": "X", "name": "HashCompilerInvocation", "args": { "durationMS": 5.37529993057251, "detail": "UnityEngine.UIModule_CodeGen.c" } },
{ "pid": 1, "tid": 94, "ts": 826448.3032226562, "dur": 3922.600030899048, "ph": "X", "name": "HashCompilerInvocation", "args": { "durationMS": 3.922600030899048, "detail": "Lump_libil2cpp_os.cpp" } },
{ "pid": 1, "tid": 94, "ts": 830391.4794921875, "dur": 5619.699954986572, "ph": "X", "name": "HashCompilerInvocation", "args": { "durationMS": 5.619699954986572, "detail": "UnityEngine.TextRenderingModule_CodeGen.c" } },
{ "pid": 1, "tid": 94, "ts": 836028.1982421875, "dur": 6404.699802398682, "ph": "X", "name": "HashCompilerInvocation", "args": { "durationMS": 6.404699802398682, "detail": "UnityEngine_Attr.cpp" } },
{ "pid": 1, "tid": 94, "ts": 842450.3784179688, "dur": 7520.199775695801, "ph": "X", "name": "HashCompilerInvocation", "args": { "durationMS": 7.520199775695801, "detail": "System.Configuration_CodeGen.c" } },
{ "pid": 1, "tid": 94, "ts": 849987.1215820312, "dur": 3234.6999645233154, "ph": "X", "name": "HashCompilerInvocation", "args": { "durationMS": 3.2346999645233154, "detail": "gc.c" } },
{ "pid": 1, "tid": 94, "ts": 853243.5913085938, "dur": 1173.799991607666, "ph": "X", "name": "HashCompilerInvocation", "args": { "durationMS": 1.173799991607666, "detail": "uncompr.c" } },
{ "pid": 1, "tid": 94, "ts": 854441.650390625, "dur": 1225.000023841858, "ph": "X", "name": "HashCompilerInvocation", "args": { "durationMS": 1.225000023841858, "detail": "compress.c" } },
{ "pid": 1, "tid": 94, "ts": 855686.4013671875, "dur": 6771.299839019775, "ph": "X", "name": "HashCompilerInvocation", "args": { "durationMS": 6.771299839019775, "detail": "Lump_libil2cpp_utils.cpp" } },
{ "pid": 1, "tid": 94, "ts": 862474.853515625, "dur": 6928.100109100342, "ph": "X", "name": "HashCompilerInvocation", "args": { "durationMS": 6.928100109100342, "detail": "Lump_libil2cpp_vm-utils.cpp" } },
{ "pid": 1, "tid": 94, "ts": 869420.8374023438, "dur": 4819.399833679199, "ph": "X", "name": "HashCompilerInvocation", "args": { "durationMS": 4.819399833679199, "detail": "Lump_libil2cpp_gc.cpp" } },
{ "pid": 1, "tid": 94, "ts": 874273.8037109375, "dur": 6374.70006942749, "ph": "X", "name": "HashCompilerInvocation", "args": { "durationMS": 6.37470006942749, "detail": "Il2CppGenericComDefinitions.cpp" } },
{ "pid": 1, "tid": 94, "ts": 880668.1518554688, "dur": 5626.299858093262, "ph": "X", "name": "HashCompilerInvocation", "args": { "durationMS": 5.626299858093262, "detail": "Il2CppGenericComDefinitions3.cpp" } },
{ "pid": 1, "tid": 94, "ts": 886316.7724609375, "dur": 4473.700046539307, "ph": "X", "name": "HashCompilerInvocation", "args": { "durationMS": 4.473700046539307, "detail": "Il2CppGenericComDefinitions6.cpp" } },
{ "pid": 1, "tid": 94, "ts": 890807.373046875, "dur": 5903.500080108643, "ph": "X", "name": "HashCompilerInvocation", "args": { "durationMS": 5.903500080108643, "detail": "Il2CppGenericComDefinitions11.cpp" } },
{ "pid": 1, "tid": 94, "ts": 896730.95703125, "dur": 7736.800193786621, "ph": "X", "name": "HashCompilerInvocation", "args": { "durationMS": 7.736800193786621, "detail": "Il2CppGenericComDefinitions14.cpp" } },
{ "pid": 1, "tid": 94, "ts": 904485.9619140625, "dur": 27056.198120117188, "ph": "X", "name": "HashCompilerInvocation", "args": { "durationMS": 27.056198120117188, "detail": "Il2CppGenericComDefinitions18.cpp" } },
{ "pid": 1, "tid": 94, "ts": 931578.0639648438, "dur": 8603.400230407715, "ph": "X", "name": "HashCompilerInvocation", "args": { "durationMS": 8.603400230407715, "detail": "Il2CppGenericComDefinitions22.cpp" } },
{ "pid": 1, "tid": 117, "ph": "M", "name": "thread_name", "args": { "name": "" } },
{ "pid": 1, "tid": 117, "ts": 642211.6088867188, "dur": 1968.999981880188, "ph": "X", "name": "HeaderFileHashProvider.HashForAllHeaderFilesReachableByFilesIn", "args": { "durationMS": 1.968999981880188, "detail": "C:\\Program Files\\Unity\\Hub\\Editor\\2021.1.16f1\\Editor\\Data\\il2cpp\\libil2cpp" } },
{ "pid": 1, "tid": 26, "ph": "M", "name": "thread_name", "args": { "name": "" } },
{ "pid": 1, "tid": 26, "ts": 738359.1918945312, "dur": 515.2000188827515, "ph": "X", "name": "HeaderFileHashProvider.HashForAllHeaderFilesReachableByFilesIn", "args": { "durationMS": 0.5152000188827515, "detail": "C:\\Program Files\\Unity\\Hub\\Editor\\2021.1.16f1\\Editor\\Data\\il2cpp\\libil2cpp" } },
{ "pid": 1, "tid": 191, "ph": "M", "name": "thread_name", "args": { "name": "" } },
{ "pid": 1, "tid": 191, "ts": 873021.5454101562, "dur": 1113.3999824523926, "ph": "X", "name": "HeaderFileHashProvider.HashForAllHeaderFilesReachableByFilesIn", "args": { "durationMS": 1.1133999824523926, "detail": "C:\\Program Files\\Unity\\Hub\\Editor\\2021.1.16f1\\Editor\\Data\\il2cpp\\external\\baselib\\Include" } },
{ "pid": 1, "tid": 184, "ph": "M", "name": "thread_name", "args": { "name": "" } },
{ "pid": 1, "tid": 184, "ts": 905147.0947265625, "dur": 1777.1999835968018, "ph": "X", "name": "HeaderFileHashProvider.HashForAllHeaderFilesReachableByFilesIn", "args": { "durationMS": 1.7771999835968018, "detail": "C:\\Program Files\\Unity\\Hub\\Editor\\2021.1.16f1\\Editor\\Data\\il2cpp\\libil2cpp" } },
{ "pid": 1, "tid": 73, "ph": "M", "name": "thread_name", "args": { "name": "" } },
{ "pid": 1, "tid": 73, "ts": 957465.087890625, "dur": 2183757.568359375, "ph": "X", "name": "Compile File", "args": { "durationMS": 2183.757568359375, "detail": "Assembly-CSharp_CodeGen.c" } },
{ "pid": 1, "tid": 74, "ph": "M", "name": "thread_name", "args": { "name": "" } },
{ "pid": 1, "tid": 74, "ts": 957467.4682617188, "dur": 2965322.75390625, "ph": "X", "name": "Compile File", "args": { "durationMS": 2965.32275390625, "detail": "Assembly-CSharp.cpp" } },
{ "pid": 1, "tid": 22, "ph": "M", "name": "thread_name", "args": { "name": "" } },
{ "pid": 1, "tid": 22, "ts": 957470.703125, "dur": 2621713.623046875, "ph": "X", "name": "Compile File", "args": { "durationMS": 2621.713623046875, "detail": "Il2CppMetadataUsage.c" } }
],
"meta_datetime": "11/25/2021 09:56:14",
"meta_command_line": "\"C:\\Program Files\\Unity\\Hub\\Editor\\2021.1.16f1\\Editor\\Data\\il2cpp\\build\\deploy\\netcoreapp3.1\\il2cpp.dll\" --compile-cpp --libil2cpp-static --platform=Android --architecture=ARM64 --configuration=Release \"--outputpath=F:\\Jogo 2D\\Jogo2D\\Library\\Il2cppBuildCache\\Android\\arm64-v8a\\Native\\arm64-v8a\\libil2cpp.so\" \"--cachedirectory=F:\\Jogo 2D\\Jogo2D\\Assets\\..\\Library\\il2cpp_android_arm64-v8a/il2cpp_cache\" \"--additional-include-directories=C:/Program Files/Unity/Hub/Editor/2021.1.16f1/Editor/Data/PlaybackEngines/AndroidPlayer/Tools\\bdwgc/include\" \"--additional-include-directories=C:/Program Files/Unity/Hub/Editor/2021.1.16f1/Editor/Data/PlaybackEngines/AndroidPlayer/Tools\\libil2cpp/include\" \"--baselib-directory=C:/Program Files/Unity/Hub/Editor/2021.1.16f1/Editor/Data/PlaybackEngines/AndroidPlayer\\Variations\\il2cpp\\Release\\StaticLibs\\arm64-v8a\" --avoid-dynamic-library-copy \"--tool-chain-path=C:/Program Files/Unity/Hub/Editor/2021.1.16f1/Editor/Data/PlaybackEngines/AndroidPlayer/NDK\" --incremental-g-c-time-slice=3 --profiler-report \"--map-file-parser=C:/Program Files/Unity/Hub/Editor/2021.1.16f1/Editor/Data/Tools/MapFileParser/MapFileParser.exe\" \"--generatedcppdir=F:/Jogo 2D/Jogo2D/Library/Il2cppBuildCache/Android/armeabi-v7a/il2cppOutput\" --dotnetprofile=unityaot",
"meta_command_line_args": "C:\\Program Files\\Unity\\Hub\\Editor\\2021.1.16f1\\Editor\\Data\\il2cpp\\build\\deploy\\netcoreapp3.1\\il2cpp.dll --compile-cpp --libil2cpp-static --platform=Android --architecture=ARM64 --configuration=Release --outputpath=F:\\Jogo 2D\\Jogo2D\\Library\\Il2cppBuildCache\\Android\\arm64-v8a\\Native\\arm64-v8a\\libil2cpp.so --cachedirectory=F:\\Jogo 2D\\Jogo2D\\Assets\\..\\Library\\il2cpp_android_arm64-v8a/il2cpp_cache --additional-include-directories=C:/Program Files/Unity/Hub/Editor/2021.1.16f1/Editor/Data/PlaybackEngines/AndroidPlayer/Tools\\bdwgc/include --additional-include-directories=C:/Program Files/Unity/Hub/Editor/2021.1.16f1/Editor/Data/PlaybackEngines/AndroidPlayer/Tools\\libil2cpp/include --baselib-directory=C:/Program Files/Unity/Hub/Editor/2021.1.16f1/Editor/Data/PlaybackEngines/AndroidPlayer\\Variations\\il2cpp\\Release\\StaticLibs\\arm64-v8a --avoid-dynamic-library-copy --tool-chain-path=C:/Program Files/Unity/Hub/Editor/2021.1.16f1/Editor/Data/PlaybackEngines/AndroidPlayer/NDK --incremental-g-c-time-slice=3 --profiler-report --map-file-parser=C:/Program Files/Unity/Hub/Editor/2021.1.16f1/Editor/Data/Tools/MapFileParser/MapFileParser.exe --generatedcppdir=F:/Jogo 2D/Jogo2D/Library/Il2cppBuildCache/Android/armeabi-v7a/il2cppOutput --dotnetprofile=unityaot",
"meta_user_name": "Informatica",
"meta_os_version": "Microsoft Windows NT 6.2.9200.0",
"meta_cpu_count": "4"}
